[
  {
    "name": "Keeb.io Iris",
    "switchMount": "cherry",
    "plate": false,
    "pcb": true
  },
  [
    {
      "y": 0.5,
      "x": 3,
      "c": "#64d168",
      "fa": [
        2
      ]
    },
    "3\n\n\n\nCam",
    {
      "x": 8.5,
      "c": "#aaaaaa"
    },
    "8"
  ],
  [
    {
      "y": -0.85,
      "x": 2,
      "c": "#64d168"
    },
    "2\n\n\n\nCam",
    {
      "x": 1
    },
    "4\n\n\n\nCam",
    {
      "x": 6.5,
      "c": "#aaaaaa"
    },
    "7",
    {
      "x": 1
    },
    "9"
  ],
  [
    {
      "y": -0.8999999999999999,
      "x": 5,
      "c": "#c77575"
    },
    "5\n\n\n\nCmd",
    {
      "x": 8.5,
      "c": "#aaaaaa"
    },
    "0"
  ],
  [
    {
      "y": -0.85,
      "c": "#6267f5",
      "fa": [
        2,
        0,
        0,
        0,
        0,
        0,
        0,
        0,
        0,
        0,
        2
      ]
    },
    "F4\n\n\n\n\n\n\n\n\n\nCancel",
    "1\n\n\n\n\n\n\n\n\n\nIdle",
    {
      "x": 7.5,
      "c": "#aaaaaa"
    },
    "F8",
    "6"
  ],
  [
    {
      "y": -0.3999999999999999,
      "x": 3,
      "c": "#8da6e3"
    },
    "E\n\n\n\nCG",
    {
      "x": 8.5
    },
    "I\n\n\n\nCG add"
  ],
  [
    {
      "y": -0.8500000000000001,
      "x": 2
    },
    "W\n\n\n\nCG",
    {
      "x": 1
    },
    "R\n\n\n\nCG",
    {
      "x": 6.5
    },
    "U\n\n\n\nCG add",
    {
      "x": 1
    },
    "O\n\n\n\nCG add"
  ],
  [
    {
      "y": -0.8999999999999999,
      "x": 5,
      "c": "#c77575"
    },
    "T\n\n\n\nCmd",
    {
      "x": 8.5,
      "c": "#aaaaaa"
    },
    "P"
  ],
  [
    {
      "y": -0.8500000000000001,
      "c": "#6267f5",
      "f": 2
    },
    "F3\n\n\n\nCG\n\n\n\n\n\nTrash",
    {
      "c": "#64d168",
      "f": 3,
      "fa": [
        2
      ]
    },
    "Q\n\n\n\nCam",
    {
      "x": 7.5,
      "c": "#aaaaaa",
      "f": 2
    },
    "F7",
    {
      "f": 3,
      "fa": [
        2
      ]
    },
    "Y"
  ],
  [
    {
      "y": -0.3999999999999999,
      "x": 3,
      "c": "#c77575"
    },
    "D\n\n\n\nCmd",
    {
      "x": 8.5
    },
    "K\n\n\n\nCmd"
  ],
  [
    {
      "y": -0.8500000000000001,
      "x": 2
    },
    "S\n\n\n\nCmd",
    {
      "x": 1,
      "c": "#8da6e3",
      "n": true
    },
    "F\n\n\n\nCG",
    {
      "x": 6.5,
      "c": "#c77575"
    },
    "J\n\n\n\nCmd",
    {
      "x": 1,
      "c": "#8da6e3",
      "n": true
    },
    "L\n\n\n\nCG add"
  ],
  [
    {
      "y": -0.8999999999999999,
      "x": 5,
      "c": "#c77575"
    },
    "G\n\n\n\nCmd",
    {
      "x": 8.5
    },
    ";\n\n\n\nCmd"
  ],
  [
    {
      "y": -0.8500000000000001,
      "c": "#8da6e3",
      "f": 4,
      "fa": [
        2
      ]
    },
    "F2\n\n\n\nCG",
    {
      "f": 3,
      "fa": [
        2
      ]
    },
    "A\n\n\n\nCG",
    {
      "x": 7.5,
      "f": 4,
      "fa": [
        2
      ]
    },
    "F6\n\n\n\nCG add",
    {
      "f": 3,
      "fa": [
        2
      ]
    },
    "H\n\n\n\nCG add"
  ],
  [
    {
      "y": -0.3999999999999999,
      "x": 3,
      "c": "#c77575"
    },
    "C\n\n\n\nCmd",
    {
      "x": 8.5
    },
    ",\n\n\n\nCmd"
  ],
  [
    {
      "y": -0.8500000000000001,
      "x": 2
    },
    "X\n\n\n\nCmd",
    {
      "x": 1,
      "c": "#8da6e3"
    },
    "V\n\n\n\nCG",
    {
      "x": 6.5,
      "c": "#c77575"
    },
    "M\n\n\n\nCmd",
    {
      "x": 1,
      "c": "#8da6e3"
    },
    ".\n\n\n\nCG add"
  ],
  [
    {
      "y": -0.9000000000000004,
      "x": 5,
      "c": "#c77575"
    },
    "B\n\n\n\nCmd",
    {
      "x": 8.5
    },
    "/\n\n\n\nCmd"
  ],
  [
    {
      "y": -0.8500000000000001,
      "c": "#8da6e3"
    },
    "F1\n\n\n\nCG",
    "Z\n\n\n\nCG",
    {
      "x": 7.5
    },
    "F5\n\n\n\nCG add",
    "N\n\n\n\nCG add"
  ],
  [
    {
      "y": -0.15000000000000036,
      "x": 3.5,
      "c": "#ebfa98"
    },
    "Fn1",
    {
      "x": 8.5
    },
    "Fn1"
  ],
  [
    {
      "y": -0.9000000000000004,
      "x": 4.5,
      "f": 2
    },
    "CTRL",
    {
      "x": 8.5
    },
    "CTRL"
  ],
  [
    {
      "r": -60,
      "rx": 0.25,
      "ry": 3,
      "y": 6,
      "x": 0.09999999999999998,
      "f": 3,
      "fa": [
        2
      ]
    },
    "SHFT",
    {
      "c": "#6267f5",
      "fa": [
        2,
        0,
        0,
        0,
        0,
        0,
        0,
        0,
        0,
        0,
        2
      ]
    },
    "SPACE\n\n\n\n\n\n\n\n\n\nAll army"
  ],
  [
    {
      "y": 7.25,
      "x": 4.85,
      "c": "#ebfa98"
    },
    "SHFT",
    {
      "c": "#aaaaaa"
    },
    "SPACE"
  ]
]
